PyCausality/TransferEntropy.py
PyCausality/__init__.py
PyCausality/Testing/__init__.py
PyCausality/Testing/integration_tests.py
PyCausality/Testing/unit_tests.py
PyCausality/Testing/Test_Utils/Integration_Fixtures.py
PyCausality/Testing/Test_Utils/Time_Series_Generate.py
PyCausality/Testing/Test_Utils/__init__.py
PyCausality/Utils/Utils.py
PyCausality/Utils/__init__.py
PyCausality-1.2.0.dist-info/METADATA
PyCausality-1.2.0.dist-info/RECORD
PyCausality-1.2.0.dist-info/WHEEL
PyCausality-1.2.0.dist-info/top_level.txt
