Metadata-Version: 2.1
Name: PyCausality
Version: 1.2.0
Summary: Extended significance testing to linear TE calculations
Home-page: https://github.com/ZacKeskin/PyCausality
Author: Zac Keskin
Author-email: Zac.Keskin.17@ucl.ac.uk
Maintainer: Zac Keskin
Maintainer-email: zackeskin@outlook.com
License: GNU GPLv3
Platform: UNKNOWN
Requires-Python: >3.5.2
Requires-Dist: pandas
Requires-Dist: statsmodels
Requires-Dist: numpy
Requires-Dist: python-dateutil (==2.6.1)
Requires-Dist: nose
